celux/__init__.py
celux/_celux.pyd
celux/_celux.pyi
celux/avcodec-61.dll
celux/avdevice-61.dll
celux/avfilter-10.dll
celux/avformat-61.dll
celux/avutil-59.dll
celux/libx264-164.dll
celux/libx265.dll
celux/py.typed
celux/swresample-5.dll
celux/swscale-8.dll
celux-0.7.3.dist-info/METADATA
celux-0.7.3.dist-info/WHEEL
celux-0.7.3.dist-info/licenses/LICENSE
celux-0.7.3.dist-info/RECORD
