Metadata-Version: 2.2
Name: celux
Version: 0.7.3
Summary: Lightspeed video decoding directly into tensors!
Keywords: ffmpeg,video,ml,pytorch,decode,tensors,inference
Author-Email: Trenton Flanagan <spigonvids@gmail.com>
License: AGPL-3.0
Classifier: Programming Language :: Python :: 3
Classifier: License :: OSI Approved :: GNU Affero General Public License v3
Classifier: Operating System :: Microsoft :: Windows
Classifier: Operating System :: POSIX :: Linux
Project-URL: Homepage, https://github.com/Trentonom0r3/celux
Project-URL: Repository, https://github.com/Trentonom0r3/celux
Project-URL: Documentation, https://github.com/Trentonom0r3/celux/blob/master/README.md
Project-URL: Changelog, https://github.com/Trentonom0r3/celux/blob/master/docs/CHANGELOG.md
Project-URL: Issues, https://github.com/Trentonom0r3/celux/issues
Requires-Python: >=3.13
